edu_eldoc_registry/__init__.py
edu_eldoc_registry/actions.py
edu_eldoc_registry/admin.py
edu_eldoc_registry/base_models.py
edu_eldoc_registry/constants.py
edu_eldoc_registry/enums.py
edu_eldoc_registry/exceptions.py
edu_eldoc_registry/models.py
edu_eldoc_registry/paths.py
edu_eldoc_registry/permissions.py
edu_eldoc_registry/py.typed
edu_eldoc_registry/typingsettings.py
edu_eldoc_registry/ui.py
edu_eldoc_registry/utils.py
edu_eldoc_registry/api/__init__.py
edu_eldoc_registry/api/common.py
edu_eldoc_registry/api/dev.py
edu_eldoc_registry/migrations/0001_initial.py
edu_eldoc_registry/migrations/0002_alter_document_status.py
edu_eldoc_registry/migrations/0003_change_certificate_date_fields_to_datetime.py
edu_eldoc_registry/migrations/__init__.py
edu_eldoc_registry/static/js/ruscrypto.min.js
edu_eldoc_registry/templates/ui-js/eldoc-sign-functions.js
edu_eldoc_registry/templates/ui-js/eldoc-sign-window.js
edu_eldoc_registry/tests/__init__.py
edu_eldoc_registry/tests/test_document.py
edu_eldoc_registry-0.5.0.dist-info/LICENSE
edu_eldoc_registry-0.5.0.dist-info/METADATA
edu_eldoc_registry-0.5.0.dist-info/WHEEL
edu_eldoc_registry-0.5.0.dist-info/top_level.txt
edu_eldoc_registry-0.5.0.dist-info/RECORD
