Metadata-Version: 2.1
Name: edu-eldoc-registry
Version: 0.5.0
Summary: Интеграция с системой Госключ
Author-email: BARS Group <education_dev@bars.group>
Project-URL: Homepage, https://stash.bars-open.ru/projects/EDUBASE/repos/edu-eldoc-registry/browse
Project-URL: Repository, https://stash.bars-open.ru/scm/edubase/edu-eldoc-registry.git
Classifier: Development Status :: 5 - Production/Stable
Classifier: Programming Language :: Python :: 3
Classifier: Programming Language :: Python :: 3.9
Classifier: Programming Language :: Python :: 3.10
Classifier: Programming Language :: Python :: 3.11
Classifier: Programming Language :: Python :: 3.12
Classifier: Framework :: Django :: 3.2
Classifier: Framework :: Django :: 4.0
Classifier: Framework :: Django :: 4.1
Classifier: Framework :: Django :: 4.2
Classifier: Framework :: Django :: 5.0
Classifier: Intended Audience :: Developers
Classifier: Environment :: Web Environment
Requires-Python: >=3.9
License-File: LICENSE
Requires-Dist: Django <5.0,>=3.2
Requires-Dist: psycopg2-binary <3,>=2.9
Requires-Dist: educommon <4,>=3.19.1
Provides-Extra: dev
Requires-Dist: isort ==5.12.0 ; extra == 'dev'
Requires-Dist: ruff ==0.12.0 ; extra == 'dev'
Requires-Dist: flake8 <7,>=4.0.1 ; extra == 'dev'
Requires-Dist: pytest <8,>=3.2.5 ; extra == 'dev'
Requires-Dist: pytest-cov <5 ; extra == 'dev'
Requires-Dist: mypy ==1.12.0 ; extra == 'dev'
Requires-Dist: pylint ==3.3.0 ; extra == 'dev'
Provides-Extra: docs
Requires-Dist: sphinx <7.5,>=7 ; extra == 'docs'
Requires-Dist: sphinx-autodoc-typehints <2.5,>=2 ; extra == 'docs'
Requires-Dist: myst-parser <3.2,>=3 ; extra == 'docs'
Requires-Dist: sphinx-design <0.7,>=0.6 ; extra == 'docs'
